[
    null,
    {
        "id": 1,
        "atypeId": 0,
        "description": "",
        "etypeId": 2,
        "traits": [
            {
                "code": 22,
                "dataId": 1,
                "value": 0
            }
        ],
        "iconIndex": 0,
        "name": "ーーーー魚ーーーー",
        "note": "",
        "params": [
            0,
            0,
            0,
            0,
            0,
            0,
            0,
            0
        ],
        "price": 0
    },
    {
        "id": 2,
        "atypeId": 1,
        "description": "【レアリティ：\\c[14]★☆☆☆\\c[0]】\nお馴染みのアイツ\\n\\n\\n----------------------------------\\n◆料理素材",
        "etypeId": 2,
        "traits": [
            {
                "code": 22,
                "dataId": 1,
                "value": 0
            }
        ],
        "iconIndex": 176,
        "name": "メダカ",
        "note": "",
        "params": [
            0,
            0,
            0,
            0,
            0,
            0,
            0,
            0
        ],
        "price": 500
    },
    {
        "id": 3,
        "atypeId": 1,
        "description": "【レアリティ：\\c[14]★☆☆☆\\c[0]】\n氷の上で釣れる奴だね\\n\\n\\n----------------------------------\\n◆料理素材",
        "etypeId": 2,
        "traits": [
            {
                "code": 22,
                "dataId": 1,
                "value": 0
            }
        ],
        "iconIndex": 177,
        "name": "ワカサギ",
        "note": "",
        "params": [
            0,
            0,
            0,
            0,
            0,
            0,
            0,
            0
        ],
        "price": 500
    },
    {
        "id": 4,
        "atypeId": 1,
        "description": "【レアリティ：\\c[14]★☆☆☆\\c[0]】\n雑草の名前じゃないよ\\n\\n\\n----------------------------------\\n◆料理素材",
        "etypeId": 2,
        "traits": [
            {
                "code": 22,
                "dataId": 1,
                "value": 0
            }
        ],
        "iconIndex": 178,
        "name": "アカザ",
        "note": "",
        "params": [
            0,
            0,
            0,
            0,
            0,
            0,
            0,
            0
        ],
        "price": 500
    },
    {
        "id": 5,
        "atypeId": 1,
        "description": "【レアリティ：\\c[14]★☆☆☆\\c[0]】\n平たい魚だなあ\\n\\n\\n----------------------------------\\n◆料理素材",
        "etypeId": 2,
        "traits": [
            {
                "code": 22,
                "dataId": 1,
                "value": 0
            }
        ],
        "iconIndex": 179,
        "name": "イトヨ",
        "note": "",
        "params": [
            0,
            0,
            0,
            0,
            0,
            0,
            0,
            0
        ],
        "price": 500
    },
    {
        "id": 6,
        "atypeId": 1,
        "description": "【レアリティ：\\c[14]★☆☆☆\\c[0]】\nショウタ君家に居る\\n\\n\\n----------------------------------\\n◆料理素材",
        "etypeId": 2,
        "traits": [
            {
                "code": 22,
                "dataId": 1,
                "value": 0
            }
        ],
        "iconIndex": 180,
        "name": "キンギョ",
        "note": "",
        "params": [
            0,
            0,
            0,
            0,
            0,
            0,
            0,
            0
        ],
        "price": 500
    },
    {
        "id": 7,
        "atypeId": 1,
        "description": "【レアリティ：\\c[14]★★☆☆\\c[0]】\n体色の黒い鯉。ふつう。\\n\\n\\n----------------------------------\\n◆料理素材",
        "etypeId": 2,
        "traits": [
            {
                "code": 22,
                "dataId": 1,
                "value": 0
            }
        ],
        "iconIndex": 181,
        "name": "マゴイ",
        "note": "",
        "params": [
            0,
            0,
            0,
            0,
            0,
            0,
            0,
            0
        ],
        "price": 1000
    },
    {
        "id": 8,
        "atypeId": 1,
        "description": "【レアリティ：\\c[14]★★☆☆\\c[0]】\n釣れてもあんま嬉しくない\\n\\n\\n----------------------------------\\n◆料理素材",
        "etypeId": 2,
        "traits": [
            {
                "code": 22,
                "dataId": 1,
                "value": 0
            }
        ],
        "iconIndex": 182,
        "name": "ボラ",
        "note": "",
        "params": [
            0,
            0,
            0,
            0,
            0,
            0,
            0,
            0
        ],
        "price": 1000
    },
    {
        "id": 9,
        "atypeId": 1,
        "description": "【レアリティ：\\c[14]★★☆☆\\c[0]】\n「脆(あ)ゆる」-弱弱しい\\n\\n\\n----------------------------------\\n◆料理素材",
        "etypeId": 2,
        "traits": [
            {
                "code": 22,
                "dataId": 1,
                "value": 0
            }
        ],
        "iconIndex": 183,
        "name": "アユ",
        "note": "",
        "params": [
            0,
            0,
            0,
            0,
            0,
            0,
            0,
            0
        ],
        "price": 1000
    },
    {
        "id": 10,
        "atypeId": 1,
        "description": "【レアリティ：\\c[14]★★☆☆\\c[0]】\n美味しくないらしい。\\n\\n\\n----------------------------------\\n◆料理素材",
        "etypeId": 2,
        "traits": [
            {
                "code": 22,
                "dataId": 1,
                "value": 0
            }
        ],
        "iconIndex": 184,
        "name": "アメマス",
        "note": "",
        "params": [
            0,
            0,
            0,
            0,
            0,
            0,
            0,
            0
        ],
        "price": 1000
    },
    {
        "id": 11,
        "atypeId": 1,
        "description": "【レアリティ：\\c[14]★★☆☆\\c[0]】\n北海道では人気の高級魚\\n\\n\\n----------------------------------\\n◆料理素材",
        "etypeId": 2,
        "traits": [
            {
                "code": 22,
                "dataId": 1,
                "value": 0
            }
        ],
        "iconIndex": 185,
        "name": "ヒメマス",
        "note": "",
        "params": [
            0,
            0,
            0,
            0,
            0,
            0,
            0,
            0
        ],
        "price": 1000
    },
    {
        "id": 12,
        "atypeId": 1,
        "description": "【レアリティ：\\c[14]★★★☆\\c[0]】\nブリッチョ\\n\\n\\n----------------------------------\\n◆料理素材",
        "etypeId": 2,
        "traits": [
            {
                "code": 22,
                "dataId": 1,
                "value": 0
            }
        ],
        "iconIndex": 192,
        "name": "ブリ",
        "note": "",
        "params": [
            0,
            0,
            0,
            0,
            0,
            0,
            0,
            0
        ],
        "price": 3000
    },
    {
        "id": 13,
        "atypeId": 1,
        "description": "【レアリティ：\\c[14]★★★☆\\c[0]】\nブリッチョもどき\\n\\n\\n----------------------------------\\n◆料理素材",
        "etypeId": 2,
        "traits": [
            {
                "code": 22,
                "dataId": 1,
                "value": 0
            }
        ],
        "iconIndex": 193,
        "name": "ブリモドキ",
        "note": "",
        "params": [
            0,
            0,
            0,
            0,
            0,
            0,
            0,
            0
        ],
        "price": 3000
    },
    {
        "id": 14,
        "atypeId": 1,
        "description": "【レアリティ：\\c[14]★★★☆\\c[0]】\nこら～！\\n\\n\\n----------------------------------\\n◆料理素材",
        "etypeId": 2,
        "traits": [
            {
                "code": 22,
                "dataId": 1,
                "value": 0
            }
        ],
        "iconIndex": 194,
        "name": "カツオ",
        "note": "",
        "params": [
            0,
            0,
            0,
            0,
            0,
            0,
            0,
            0
        ],
        "price": 3000
    },
    {
        "id": 15,
        "atypeId": 1,
        "description": "【レアリティ：\\c[14]★★★☆\\c[0]】\n刺身おいしいですよね\\n\\n\\n----------------------------------\\n◆料理素材",
        "etypeId": 2,
        "traits": [
            {
                "code": 22,
                "dataId": 1,
                "value": 0
            }
        ],
        "iconIndex": 195,
        "name": "キハダマグロ",
        "note": "",
        "params": [
            0,
            0,
            0,
            0,
            0,
            0,
            0,
            0
        ],
        "price": 3000
    },
    {
        "id": 16,
        "atypeId": 1,
        "description": "【レアリティ：\\c[14]★★★☆\\c[0]】\n横スマ-横スマッシュ攻撃\\n\\n\\n----------------------------------\\n◆料理素材",
        "etypeId": 2,
        "traits": [
            {
                "code": 22,
                "dataId": 1,
                "value": 0
            }
        ],
        "iconIndex": 196,
        "name": "スマ",
        "note": "",
        "params": [
            0,
            0,
            0,
            0,
            0,
            0,
            0,
            0
        ],
        "price": 3000
    },
    {
        "id": 17,
        "atypeId": 1,
        "description": "【レアリティ：\\c[14]★★★★\\c[0]】\nマグロ類では安いんだと。\\n\\n\\n----------------------------------\\n◆料理素材",
        "etypeId": 2,
        "traits": [
            {
                "code": 22,
                "dataId": 1,
                "value": 0
            }
        ],
        "iconIndex": 197,
        "name": "ビンナガマグロ",
        "note": "",
        "params": [
            0,
            0,
            0,
            0,
            0,
            0,
            0,
            0
        ],
        "price": 5000
    },
    {
        "id": 18,
        "atypeId": 1,
        "description": "【レアリティ：\\c[14]★★★★\\c[0]】\nそらそうだ。に似てる。\\n\\n\\n----------------------------------\\n◆料理素材",
        "etypeId": 2,
        "traits": [
            {
                "code": 22,
                "dataId": 1,
                "value": 0
            }
        ],
        "iconIndex": 198,
        "name": "ヒラソウダ",
        "note": "",
        "params": [
            0,
            0,
            0,
            0,
            0,
            0,
            0,
            0
        ],
        "price": 5000
    },
    {
        "id": 19,
        "atypeId": 1,
        "description": "【レアリティ：\\c[14]★★★★\\c[0]】\n目、バチィ！\\n\\n\\n----------------------------------\\n◆料理素材",
        "etypeId": 2,
        "traits": [
            {
                "code": 22,
                "dataId": 1,
                "value": 0
            }
        ],
        "iconIndex": 199,
        "name": "メバチ",
        "note": "",
        "params": [
            0,
            0,
            0,
            0,
            0,
            0,
            0,
            0
        ],
        "price": 5000
    },
    {
        "id": 20,
        "atypeId": 1,
        "description": "【レアリティ：\\c[14]★★★★\\c[0]】\n魚の中でも特に美味い！\\n\\n\\n----------------------------------\\n◆料理素材",
        "etypeId": 2,
        "traits": [
            {
                "code": 22,
                "dataId": 1,
                "value": 0
            }
        ],
        "iconIndex": 200,
        "name": "マナガツオ",
        "note": "",
        "params": [
            0,
            0,
            0,
            0,
            0,
            0,
            0,
            0
        ],
        "price": 5000
    },
    {
        "id": 21,
        "atypeId": 1,
        "description": "【レアリティ：\\c[14]★★★★\\c[0]】\nなんでこんなの釣れるの。\\n\\n\\n----------------------------------\\n◆料理素材",
        "etypeId": 2,
        "traits": [
            {
                "code": 22,
                "dataId": 1,
                "value": 0
            }
        ],
        "iconIndex": 201,
        "name": "メカジキ",
        "note": "",
        "params": [
            0,
            0,
            0,
            0,
            0,
            0,
            0,
            0
        ],
        "price": 5000
    },
    {
        "id": 22,
        "atypeId": 0,
        "description": "【レアリティ：\\c[14]★☆☆☆\\c[0]】\nありふれた根菜。\\n\\n\\n----------------------------------\\n◆料理素材",
        "etypeId": 2,
        "traits": [
            {
                "code": 22,
                "dataId": 1,
                "value": 0
            }
        ],
        "iconIndex": 256,
        "name": "にんじん",
        "note": "",
        "params": [
            0,
            0,
            0,
            0,
            0,
            0,
            0,
            0
        ],
        "price": 150
    },
    {
        "id": 23,
        "atypeId": 0,
        "description": "【レアリティ：\\c[14]★☆☆☆\\c[0]】\n便利な野菜。\\n\\n\\n----------------------------------\\n◆料理素材",
        "etypeId": 2,
        "traits": [
            {
                "code": 22,
                "dataId": 1,
                "value": 0
            }
        ],
        "iconIndex": 257,
        "name": "たまねぎ",
        "note": "",
        "params": [
            0,
            0,
            0,
            0,
            0,
            0,
            0,
            0
        ],
        "price": 150
    },
    {
        "id": 24,
        "atypeId": 0,
        "description": "【レアリティ：\\c[14]★☆☆☆\\c[0]】\n煮ても焼いても蒸しても！\\n\\n\\n----------------------------------\\n◆料理素材",
        "etypeId": 2,
        "traits": [
            {
                "code": 22,
                "dataId": 1,
                "value": 0
            }
        ],
        "iconIndex": 258,
        "name": "じゃがいも",
        "note": "",
        "params": [
            0,
            0,
            0,
            0,
            0,
            0,
            0,
            0
        ],
        "price": 200
    },
    {
        "id": 25,
        "atypeId": 0,
        "description": "【レアリティ：\\c[14]★☆☆☆\\c[0]】\n素朴な甘さがおいしい。\\n\\n\\n----------------------------------\\n◆料理素材",
        "etypeId": 2,
        "traits": [
            {
                "code": 22,
                "dataId": 1,
                "value": 0
            }
        ],
        "iconIndex": 259,
        "name": "さつまいも",
        "note": "",
        "params": [
            0,
            0,
            0,
            0,
            0,
            0,
            0,
            0
        ],
        "price": 200
    },
    {
        "id": 26,
        "atypeId": 0,
        "description": "【レアリティ：\\c[14]★☆☆☆\\c[0]】\n日本の主食！\\n\\n\\n----------------------------------\\n◆料理素材",
        "etypeId": 2,
        "traits": [
            {
                "code": 22,
                "dataId": 1,
                "value": 0
            }
        ],
        "iconIndex": 260,
        "name": "米",
        "note": "",
        "params": [
            0,
            0,
            0,
            0,
            0,
            0,
            0,
            0
        ],
        "price": 300
    },
    {
        "id": 27,
        "atypeId": 0,
        "description": "【レアリティ：\\c[14]★☆☆☆\\c[0]】\n疲労回復や滋養強壮に。\\n\\n\\n----------------------------------\\n◆料理素材",
        "etypeId": 2,
        "traits": [
            {
                "code": 22,
                "dataId": 1,
                "value": 0
            }
        ],
        "iconIndex": 261,
        "name": "にんにく",
        "note": "",
        "params": [
            0,
            0,
            0,
            0,
            0,
            0,
            0,
            0
        ],
        "price": 150
    },
    {
        "id": 28,
        "atypeId": 0,
        "description": "【レアリティ：\\c[14]★☆☆☆\\c[0]】\nいろいろなお料理に。\\nコレステロールゼロ。\\n\\n----------------------------------\\n◆料理素材",
        "etypeId": 2,
        "traits": [
            {
                "code": 22,
                "dataId": 1,
                "value": 0
            }
        ],
        "iconIndex": 262,
        "name": "油",
        "note": "",
        "params": [
            0,
            0,
            0,
            0,
            0,
            0,
            0,
            0
        ],
        "price": 200
    },
    {
        "id": 29,
        "atypeId": 0,
        "description": "【レアリティ：\\c[14]★☆☆☆\\c[0]】\n天然の海水塩。\\n\\n\\n----------------------------------\\n◆料理素材",
        "etypeId": 2,
        "traits": [
            {
                "code": 22,
                "dataId": 1,
                "value": 0
            }
        ],
        "iconIndex": 263,
        "name": "塩",
        "note": "",
        "params": [
            0,
            0,
            0,
            0,
            0,
            0,
            0,
            0
        ],
        "price": 100
    },
    {
        "id": 30,
        "atypeId": 0,
        "description": "【レアリティ：\\c[14]★☆☆☆\\c[0]】\nすっぱい柑橘類。\\n\\n\\n----------------------------------\\n◆料理素材",
        "etypeId": 2,
        "traits": [
            {
                "code": 22,
                "dataId": 1,
                "value": 0
            }
        ],
        "iconIndex": 264,
        "name": "レモン",
        "note": "",
        "params": [
            0,
            0,
            0,
            0,
            0,
            0,
            0,
            0
        ],
        "price": 200
    },
    {
        "id": 31,
        "atypeId": 0,
        "description": "【レアリティ：\\c[14]★★☆☆\\c[0]】\n透き通ったきれいな天然水。\\n飲用可能。\\n\\n----------------------------------\\n◆料理素材",
        "etypeId": 2,
        "traits": [
            {
                "code": 22,
                "dataId": 1,
                "value": 0
            }
        ],
        "iconIndex": 272,
        "name": "きれいな水",
        "note": "山菜マン",
        "params": [
            0,
            0,
            0,
            0,
            0,
            0,
            0,
            0
        ],
        "price": 250
    },
    {
        "id": 32,
        "atypeId": 0,
        "description": "【レアリティ：\\c[14]★★☆☆\\c[0]】\nありふれた食用のきのこ。\\nぷりぷりの食感！\\n\\n----------------------------------\\n◆料理素材",
        "etypeId": 2,
        "traits": [
            {
                "code": 22,
                "dataId": 1,
                "value": 0
            }
        ],
        "iconIndex": 273,
        "name": "しめじ",
        "note": "山菜マン",
        "params": [
            0,
            0,
            0,
            0,
            0,
            0,
            0,
            0
        ],
        "price": 200
    },
    {
        "id": 33,
        "atypeId": 0,
        "description": "【レアリティ：\\c[14]★★☆☆\\c[0]】\n生でも干しでもおいしいきのこ。\\n旨味たっぷり！\\n\\n----------------------------------\\n◆料理素材",
        "etypeId": 2,
        "traits": [
            {
                "code": 22,
                "dataId": 1,
                "value": 0
            }
        ],
        "iconIndex": 274,
        "name": "しいたけ",
        "note": "山菜マン",
        "params": [
            0,
            0,
            0,
            0,
            0,
            0,
            0,
            0
        ],
        "price": 300
    },
    {
        "id": 34,
        "atypeId": 0,
        "description": "【レアリティ：\\c[14]★★☆☆\\c[0]】\nクセのない味わいのきのこ。\\nシャッキリ食感！\\n\\n----------------------------------\\n◆料理素材",
        "etypeId": 2,
        "traits": [
            {
                "code": 22,
                "dataId": 1,
                "value": 0
            }
        ],
        "iconIndex": 275,
        "name": "エリンギ",
        "note": "山菜マン",
        "params": [
            0,
            0,
            0,
            0,
            0,
            0,
            0,
            0
        ],
        "price": 400
    },
    {
        "id": 35,
        "atypeId": 0,
        "description": "【レアリティ：\\c[14]★★★★\\c[0]】\n伝説のきのこ。\\n学名はTricholoma matsutake\\n\\n----------------------------------\\n◆料理素材",
        "etypeId": 2,
        "traits": [
            {
                "code": 22,
                "dataId": 1,
                "value": 0
            }
        ],
        "iconIndex": 276,
        "name": "松茸",
        "note": "山菜マン",
        "params": [
            0,
            0,
            0,
            0,
            0,
            0,
            0,
            0
        ],
        "price": 4000
    },
    {
        "id": 36,
        "atypeId": 0,
        "description": "【レアリティ：\\c[14]★★★☆\\c[0]】\n山野に自生していることがある。\\n食べられる植物。\\n\\n----------------------------------\\n◆料理素材",
        "etypeId": 2,
        "traits": [
            {
                "code": 22,
                "dataId": 1,
                "value": 0
            }
        ],
        "iconIndex": 277,
        "name": "山菜",
        "note": "山菜マン",
        "params": [
            0,
            0,
            0,
            0,
            0,
            0,
            0,
            0
        ],
        "price": 1000
    },
    {
        "id": 37,
        "atypeId": 0,
        "description": "【レアリティ：\\c[14]★★★☆\\c[0]】\n独特の辛みが癖になる香辛料。\\n\\n\\n----------------------------------\\n◆料理素材",
        "etypeId": 2,
        "traits": [
            {
                "code": 22,
                "dataId": 1,
                "value": 0
            }
        ],
        "iconIndex": 278,
        "name": "山椒",
        "note": "山菜マン",
        "params": [
            0,
            0,
            0,
            0,
            0,
            0,
            0,
            0
        ],
        "price": 1500
    },
    {
        "id": 38,
        "atypeId": 0,
        "description": "【レアリティ：\\c[14]★☆☆☆\\c[0]】\nその辺に落ちている木の枝。\\n食材…？\\n\\n----------------------------------\\n◆料理素材",
        "etypeId": 2,
        "traits": [
            {
                "code": 22,
                "dataId": 1,
                "value": 0
            }
        ],
        "iconIndex": 279,
        "name": "木の枝",
        "note": "山菜マン",
        "params": [
            0,
            0,
            0,
            0,
            0,
            0,
            0,
            0
        ],
        "price": 10
    }
]